pvWebMonitor/__init__.py
pvWebMonitor/config_1_0.xsd
pvWebMonitor/config_1_0_1.xsd
pvWebMonitor/dev_main.py
pvWebMonitor/main.py
pvWebMonitor/pvlist-gp.xml
pvWebMonitor/pvlist.xsd
pvWebMonitor/pvwatch.py
pvWebMonitor/read_config.py
pvWebMonitor/setup.py
pvWebMonitor/utils.py
pvWebMonitor/project/config.xml
pvWebMonitor/project/index.xsl
pvWebMonitor/project/livedata.xsl
pvWebMonitor/project/manage.sh
pvWebMonitor/project/pvlist.xml
pvWebMonitor/project/pvlist.xsl
pvWebMonitor/project/rawdata.xsl
pvWebMonitor/tests/__init__.py
pvWebMonitor/tests/test_pvwatch.py
pvwebmonitor-2021.0.2.dist-info/licenses/LICENSE
pvwebmonitor-2021.0.2.dist-info/METADATA
pvwebmonitor-2021.0.2.dist-info/WHEEL
pvwebmonitor-2021.0.2.dist-info/entry_points.txt
pvwebmonitor-2021.0.2.dist-info/top_level.txt
pvwebmonitor-2021.0.2.dist-info/RECORD
